fnfqueue/__init__.py
fnfqueue/_fnfqueue.pypy38-pp73-x86_64-linux-gnu.so
fnfqueue-1.1.2.dist-info/top_level.txt
fnfqueue-1.1.2.dist-info/LICENSE
fnfqueue-1.1.2.dist-info/RECORD
fnfqueue-1.1.2.dist-info/WHEEL
fnfqueue-1.1.2.dist-info/METADATA
