Metadata-Version: 2.1
Name: fnfqueue
Version: 1.1.2
Summary: Fast python library encapsulating the nfqueue netlink interface.
Home-page: https://github.com/notti/fnfqueue
Author: Gernot Vormayr
Author-email: gvormayr@gmail.com
License: MIT
Keywords: nfqueue netfilter netlink iptables firewall mangle
Platform: UNKNOWN
Classifier: Development Status :: 5 - Production/Stable
Classifier: Environment :: Other Environment
Classifier: Intended Audience :: Developers
Classifier: Intended Audience :: Telecommunications Industry
Classifier: Intended Audience :: Information Technology
Classifier: License :: OSI Approved :: MIT License
Classifier: Operating System :: POSIX :: Linux
Classifier: Programming Language :: C
Classifier: Programming Language :: Python
Classifier: Programming Language :: Python :: 3
Classifier: Programming Language :: Python :: 3.8
Classifier: Programming Language :: Python :: 3.9
Classifier: Programming Language :: Python :: 3.10
Classifier: Programming Language :: Python :: 3.11
Classifier: Programming Language :: Python :: Implementation :: PyPy
Classifier: Topic :: Internet
Classifier: Topic :: Security
Classifier: Topic :: Software Development :: Libraries
Classifier: Topic :: System :: Operating System Kernels :: Linux
License-File: LICENSE
Requires-Dist: cffi (>=1.0.0)
